databricks_genai_sdlc-0.1.4.dist-info/licenses/LICENSE
sdlc_databricks/__init__.py
sdlc_databricks/core.py
databricks_genai_sdlc-0.1.4.dist-info/METADATA
databricks_genai_sdlc-0.1.4.dist-info/WHEEL
databricks_genai_sdlc-0.1.4.dist-info/top_level.txt
databricks_genai_sdlc-0.1.4.dist-info/RECORD
