Metadata-Version: 2.4
Name: databricks-genai-sdlc
Version: 0.1.4
Summary: A library for SDLC automation on Databricks with GitHub and Databricks AI integration.
Author-email: "Dhrubojyoti Mukherjee, Rahul Gupta" <genaiusecases0101@gmail.com>
License: MIT
Project-URL: Homepage, https://github.com/yourusername/databricks-genai-sdlc
Project-URL: Bug Tracker, https://github.com/yourusername/databricks-genai-sdlc/issues
Keywords: databricks,pyspark,sdlc,automation,genai
Classifier: Programming Language :: Python :: 3
Classifier: License :: OSI Approved :: MIT License
Classifier: Operating System :: OS Independent
Requires-Python: >=3.8
License-File: LICENSE
Requires-Dist: requests
Requires-Dist: pandas
Requires-Dist: pymupdf
Dynamic: license-file
